{"nodes": [{"id": "parcourscandidatclient", "label": "ParcoursCandidatClient.tsx", "file_type": "code", "source_file": "src\\components\\parcours\\ParcoursCandidatClient.tsx", "source_location": "L1"}, {"id": "parcourscandidatclient_weeksuntilexam", "label": "weeksUntilExam()", "file_type": "code", "source_file": "src\\components\\parcours\\ParcoursCandidatClient.tsx", "source_location": "L19"}, {"id": "parcourscandidatclient_daysuntilexam", "label": "daysUntilExam()", "file_type": "code", "source_file": "src\\components\\parcours\\ParcoursCandidatClient.tsx", "source_location": "L25"}, {"id": "parcourscandidatclient_readchecklist", "label": "readChecklist()", "file_type": "code", "source_file": "src\\components\\parcours\\ParcoursCandidatClient.tsx", "source_location": "L150"}, {"id": "parcourscandidatclient_writechecklist", "label": "writeChecklist()", "file_type": "code", "source_file": "src\\components\\parcours\\ParcoursCandidatClient.tsx", "source_location": "L162"}, {"id": "parcourscandidatclient_parcourscandidatclient", "label": "ParcoursCandidatClient()", "file_type": "code", "source_file": "src\\components\\parcours\\ParcoursCandidatClient.tsx", "source_location": "L170"}], "edges": [{"source": "parcourscandidatclient", "target": "react", "relation": "imports_from", "confidence": "EXTRACTED", "source_file": "src\\components\\parcours\\ParcoursCandidatClient.tsx", "source_location": "L3", "weight": 1.0}, {"source": "parcourscandidatclient", "target": "link", "relation": "imports_from", "confidence": "EXTRACTED", "source_file": "src\\components\\parcours\\ParcoursCandidatClient.tsx", "source_location": "L4", "weight": 1.0}, {"source": "parcourscandidatclient", "target": "lucide_react", "relation": "imports_from", "confidence": "EXTRACTED", "source_file": "src\\components\\parcours\\ParcoursCandidatClient.tsx", "source_location": "L5", "weight": 1.0}, {"source": "parcourscandidatclient", "target": "interiorpageshell", "relation": "imports_from", "confidence": "EXTRACTED", "source_file": "src\\components\\parcours\\ParcoursCandidatClient.tsx", "source_location": "L7", "weight": 1.0}, {"source": "parcourscandidatclient", "target": "revisionthemesjourney", "relation": "imports_from", "confidence": "EXTRACTED", "source_file": "src\\components\\parcours\\ParcoursCandidatClient.tsx", "source_location": "L8", "weight": 1.0}, {"source": "parcourscandidatclient", "target": "progressring", "relation": "imports_from", "confidence": "EXTRACTED", "source_file": "src\\components\\parcours\\ParcoursCandidatClient.tsx", "source_location": "L9", "weight": 1.0}, {"source": "parcourscandidatclient", "target": "sectiontitle", "relation": "imports_from", "confidence": "EXTRACTED", "source_file": "src\\components\\parcours\\ParcoursCandidatClient.tsx", "source_location": "L10", "weight": 1.0}, {"source": "parcourscandidatclient", "target": "interior_shell_glow", "relation": "imports_from", "confidence": "EXTRACTED", "source_file": "src\\components\\parcours\\ParcoursCandidatClient.tsx", "source_location": "L11", "weight": 1.0}, {"source": "parcourscandidatclient", "target": "cn", "relation": "imports_from", "confidence": "EXTRACTED", "source_file": "src\\components\\parcours\\ParcoursCandidatClient.tsx", "source_location": "L12", "weight": 1.0}, {"source": "parcourscandidatclient", "target": "parcourscandidatclient_weeksuntilexam", "relation": "contains", "confidence": "EXTRACTED", "source_file": "src\\components\\parcours\\ParcoursCandidatClient.tsx", "source_location": "L19", "weight": 1.0}, {"source": "parcourscandidatclient", "target": "parcourscandidatclient_daysuntilexam", "relation": "contains", "confidence": "EXTRACTED", "source_file": "src\\components\\parcours\\ParcoursCandidatClient.tsx", "source_location": "L25", "weight": 1.0}, {"source": "parcourscandidatclient", "target": "parcourscandidatclient_readchecklist", "relation": "contains", "confidence": "EXTRACTED", "source_file": "src\\components\\parcours\\ParcoursCandidatClient.tsx", "source_location": "L150", "weight": 1.0}, {"source": "parcourscandidatclient", "target": "parcourscandidatclient_writechecklist", "relation": "contains", "confidence": "EXTRACTED", "source_file": "src\\components\\parcours\\ParcoursCandidatClient.tsx", "source_location": "L162", "weight": 1.0}, {"source": "parcourscandidatclient", "target": "parcourscandidatclient_parcourscandidatclient", "relation": "contains", "confidence": "EXTRACTED", "source_file": "src\\components\\parcours\\ParcoursCandidatClient.tsx", "source_location": "L170", "weight": 1.0}, {"source": "parcourscandidatclient_parcourscandidatclient", "target": "parcourscandidatclient_weeksuntilexam", "relation": "calls", "confidence": "EXTRACTED", "source_file": "src\\components\\parcours\\ParcoursCandidatClient.tsx", "source_location": "L198", "weight": 1.0}, {"source": "parcourscandidatclient_parcourscandidatclient", "target": "parcourscandidatclient_daysuntilexam", "relation": "calls", "confidence": "EXTRACTED", "source_file": "src\\components\\parcours\\ParcoursCandidatClient.tsx", "source_location": "L199", "weight": 1.0}]}