{"nodes": [{"id": "articulation_check", "label": "articulation-check.ts", "file_type": "code", "source_file": "src\\components\\entrainement\\articulation-check.ts", "source_location": "L1"}, {"id": "articulation_check_normalizetitrearticulation", "label": "normalizeTitreArticulation()", "file_type": "code", "source_file": "src\\components\\entrainement\\articulation-check.ts", "source_location": "L2"}, {"id": "articulation_check_titrecartouchematchereference", "label": "titreCartoucheMatcheReference()", "file_type": "code", "source_file": "src\\components\\entrainement\\articulation-check.ts", "source_location": "L11"}, {"id": "articulation_check_evaluercartouchesparressource", "label": "evaluerCartouchesParRessource()", "file_type": "code", "source_file": "src\\components\\entrainement\\articulation-check.ts", "source_location": "L28"}], "edges": [{"source": "articulation_check", "target": "articulation_check_normalizetitrearticulation", "relation": "contains", "confidence": "EXTRACTED", "source_file": "src\\components\\entrainement\\articulation-check.ts", "source_location": "L2", "weight": 1.0}, {"source": "articulation_check", "target": "articulation_check_titrecartouchematchereference", "relation": "contains", "confidence": "EXTRACTED", "source_file": "src\\components\\entrainement\\articulation-check.ts", "source_location": "L11", "weight": 1.0}, {"source": "articulation_check", "target": "articulation_check_evaluercartouchesparressource", "relation": "contains", "confidence": "EXTRACTED", "source_file": "src\\components\\entrainement\\articulation-check.ts", "source_location": "L28", "weight": 1.0}, {"source": "articulation_check_titrecartouchematchereference", "target": "articulation_check_normalizetitrearticulation", "relation": "calls", "confidence": "EXTRACTED", "source_file": "src\\components\\entrainement\\articulation-check.ts", "source_location": "L12", "weight": 1.0}]}