{"nodes": [{"id": "coursemodulejsonld", "label": "CourseModuleJsonLd.tsx", "file_type": "code", "source_file": "src\\components\\cours\\CourseModuleJsonLd.tsx", "source_location": "L1"}, {"id": "coursemodulejsonld_coursemodulejsonld", "label": "CourseModuleJsonLd()", "file_type": "code", "source_file": "src\\components\\cours\\CourseModuleJsonLd.tsx", "source_location": "L6"}], "edges": [{"source": "coursemodulejsonld", "target": "fascicules_list", "relation": "imports_from", "confidence": "EXTRACTED", "source_file": "src\\components\\cours\\CourseModuleJsonLd.tsx", "source_location": "L1", "weight": 1.0}, {"source": "coursemodulejsonld", "target": "site_url", "relation": "imports_from", "confidence": "EXTRACTED", "source_file": "src\\components\\cours\\CourseModuleJsonLd.tsx", "source_location": "L2", "weight": 1.0}, {"source": "coursemodulejsonld", "target": "coursemodulejsonld_coursemodulejsonld", "relation": "contains", "confidence": "EXTRACTED", "source_file": "src\\components\\cours\\CourseModuleJsonLd.tsx", "source_location": "L6", "weight": 1.0}]}