{"nodes": [{"id": "plainte_sdcp_shared", "label": "plainte-sdcp-shared.ts", "file_type": "code", "source_file": "src\\data\\modeles-pv\\plainte-sdcp-shared.ts", "source_location": "L1"}, {"id": "plainte_sdcp_shared_renumberrubriquesapartirde", "label": "renumberRubriquesAPartirDe()", "file_type": "code", "source_file": "src\\data\\modeles-pv\\plainte-sdcp-shared.ts", "source_location": "L190"}], "edges": [{"source": "plainte_sdcp_shared", "target": "pv", "relation": "imports_from", "confidence": "EXTRACTED", "source_file": "src\\data\\modeles-pv\\plainte-sdcp-shared.ts", "source_location": "L1", "weight": 1.0}, {"source": "plainte_sdcp_shared", "target": "plainte_sdcp_shared_renumberrubriquesapartirde", "relation": "contains", "confidence": "EXTRACTED", "source_file": "src\\data\\modeles-pv\\plainte-sdcp-shared.ts", "source_location": "L190", "weight": 1.0}]}