{"nodes": [{"id": "copybox", "label": "CopyBox.tsx", "file_type": "code", "source_file": "src\\components\\ui\\CopyBox.tsx", "source_location": "L1"}, {"id": "copybox_copy", "label": "copy()", "file_type": "code", "source_file": "src\\components\\ui\\CopyBox.tsx", "source_location": "L18"}], "edges": [{"source": "copybox", "target": "react", "relation": "imports_from", "confidence": "EXTRACTED", "source_file": "src\\components\\ui\\CopyBox.tsx", "source_location": "L3", "weight": 1.0}, {"source": "copybox", "target": "lucide_react", "relation": "imports_from", "confidence": "EXTRACTED", "source_file": "src\\components\\ui\\CopyBox.tsx", "source_location": "L4", "weight": 1.0}, {"source": "copybox", "target": "cn", "relation": "imports_from", "confidence": "EXTRACTED", "source_file": "src\\components\\ui\\CopyBox.tsx", "source_location": "L6", "weight": 1.0}, {"source": "copybox", "target": "copybox_copy", "relation": "contains", "confidence": "EXTRACTED", "source_file": "src\\components\\ui\\CopyBox.tsx", "source_location": "L18", "weight": 1.0}]}